tap_rest_api/__init__.py
tap_rest_api/default_spec.json
tap_rest_api/helper.py
tap_rest_api/main.py
tap_rest_api/schema.py
tap_rest_api/sync.py
tap_rest_api-0.2.14.dist-info/licenses/AUTHORS.md
tap_rest_api-0.2.14.dist-info/licenses/LICENSE
tap_rest_api-0.2.14.dist-info/METADATA
tap_rest_api-0.2.14.dist-info/WHEEL
tap_rest_api-0.2.14.dist-info/entry_points.txt
tap_rest_api-0.2.14.dist-info/top_level.txt
tap_rest_api-0.2.14.dist-info/RECORD
