Metadata-Version: 2.4
Name: tap-rest-api
Version: 0.2.14
Summary: Singer.io tap for extracting data from any REST API
Author: Daigo Tanaka
License-Expression: Apache-2.0
Project-URL: Homepage, https://github.com/anelendata/tap-rest-api
Classifier: Development Status :: 4 - Beta
Classifier: Operating System :: MacOS :: MacOS X
Classifier: Operating System :: POSIX :: Linux
Classifier: Programming Language :: Python :: 3.9
Classifier: Programming Language :: Python :: 3.10
Classifier: Programming Language :: Python :: 3.11
Classifier: Programming Language :: Python :: 3.12
Requires-Python: >=3.9
License-File: LICENSE
License-File: AUTHORS.md
Requires-Dist: attrs==25.3.0
Requires-Dist: backoff>=1.8.0
Requires-Dist: getschema>=0.2.11
Requires-Dist: jsonschema<3.dev0,>=2.6.0
Requires-Dist: python-dateutil==2.9.0.post0
Requires-Dist: requests==2.32.5
Requires-Dist: simplejson==3.13.2
Requires-Dist: singer-python==6.1.1
Dynamic: license-file
